render_static/__init__.py
render_static/apps.py
render_static/context.py
render_static/engine.py
render_static/exceptions.py
render_static/origin.py
render_static/placeholders.py
render_static/resource.py
render_static/backends/__init__.py
render_static/backends/base.py
render_static/backends/django.py
render_static/backends/jinja2.py
render_static/loaders/__init__.py
render_static/loaders/django.py
render_static/loaders/jinja2.py
render_static/loaders/mixins.py
render_static/loaders/utils.py
render_static/management/__init__.py
render_static/management/completers.py
render_static/management/commands/__init__.py
render_static/management/commands/renderstatic.py
render_static/static_templates/render_static/defines.js
render_static/static_templates/render_static/enums.js
render_static/static_templates/render_static/urls.js
render_static/templatetags/__init__.py
render_static/templatetags/render_static.py
render_static/transpilers/__init__.py
render_static/transpilers/base.py
render_static/transpilers/defines_to_js.py
render_static/transpilers/enums_to_js.py
render_static/transpilers/urls_to_js.py
django_render_static-3.5.1.dist-info/METADATA
django_render_static-3.5.1.dist-info/WHEEL
django_render_static-3.5.1.dist-info/licenses/LICENSE
django_render_static-3.5.1.dist-info/RECORD
