Metadata-Version: 2.4
Name: django-render-static
Version: 3.5.1
Summary: Use Django's template engine to render static files at deployment or package time. Includes transpilers for extending Django's url reversal and enums to JavaScript.
Project-URL: Homepage, https://django-render-static.readthedocs.io
Project-URL: Documentation, https://django-render-static.readthedocs.io
Project-URL: Repository, https://github.com/bckohan/django-render-static
Project-URL: Issues, https://github.com/bckohan/django-render-static/issues
Project-URL: Changelog, https://django-render-static.readthedocs.io/en/stable/changelog.html
Project-URL: Code_of_Conduct, https://github.com/bckohan/django-render-static/blob/main/CODE_OF_CONDUCT.md
Author-email: Brian Kohan <bckohan@gmail.com>
License-Expression: MIT
License-File: LICENSE
Keywords: defines,django,enum,javascript,reverse,static,templates,transpile,transpiler,url
Classifier: Development Status :: 5 - Production/Stable
Classifier: Environment :: Console
Classifier: Framework :: Django
Classifier: Framework :: Django :: 4.2
Classifier: Framework :: Django :: 5.2
Classifier: Framework :: Django :: 6.0
Classifier: Intended Audience :: Developers
Classifier: License :: OSI Approved :: MIT License
Classifier: Natural Language :: English
Classifier: Operating System :: OS Independent
Classifier: Programming Language :: Python
Classifier: Programming Language :: Python :: 3.10
Classifier: Programming Language :: Python :: 3.11
Classifier: Programming Language :: Python :: 3.12
Classifier: Programming Language :: Python :: 3.13
Classifier: Programming Language :: Python :: 3.14
Classifier: Topic :: Internet :: WWW/HTTP
Classifier: Topic :: Internet :: WWW/HTTP :: Site Management
Classifier: Topic :: Software Development :: Libraries
Classifier: Topic :: Software Development :: Libraries :: Python Modules
Requires-Python: <4.0,>=3.10
Requires-Dist: django-typer<4.0,>=3.0
Requires-Dist: django<6.1,>=4.2
Provides-Extra: jinja2
Requires-Dist: jinja2<4.0,>=2.9; extra == 'jinja2'
Provides-Extra: pyyaml
Requires-Dist: pyyaml<7.0,>=5.1; extra == 'pyyaml'
